{
  "timestamp": "2025-10-24T15:07:54.243144",
  "content": "I apologize, but I don't see any specific information provided about Nacho Echegoyen's background, work, or interests in the prompt. Without concrete details about their profile, I cannot provide a meaningful analysis.\n\nTo provide a thorough and accurate analysis as requested, I would need information about:\n\n1. Their academic/professional background\n2. Current work and research interests\n3. Experience with Active Inference\n4. Specific goals for participating in the symposium\n5. Current projects or applications\n6. Technical expertise and domain knowledge\n7. Learning objectives\n8. Challenges they're facing\n9. Future aspirations in the field\n\nIf you could provide these details about Nacho Echegoyen, I would be happy to analyze their profile according to the comprehensive framework you've outlined, including:\n- Expertise assessment\n- Learning opportunities\n- Research interests alignment\n- Collaboration potential\n- Symposium participation strategy\n- Development roadmap\n- Active Inference integration\n\nPlease share any available information about Nacho Echegoyen so I can provide a meaningful analysis.",
  "metadata": {
    "participant": "Nacho Echegoyen",
    "report_type": "profile_analysis"
  }
}