{
  "timestamp": "2025-11-07T15:27:55.948993",
  "content": "I apologize, but I notice that the profile information sections for Greg Elliott are blank in your query. Without specific information about Greg Elliott's background, current work, goals, and interests, I cannot provide a detailed or accurate analysis.\n\nTo provide a meaningful profile analysis, I would need information about:\n\n1. Greg's professional/academic background\n2. Current work and research interests\n3. Experience level with Active Inference\n4. Specific goals for participating in the symposium\n5. Current challenges and learning objectives\n6. Areas of expertise and technical skills\n7. Target applications or research directions\n\nIf you could provide these details about Greg Elliott, I would be happy to conduct a comprehensive profile analysis addressing all the requested categories:\n- Expertise Assessment\n- Learning Opportunities\n- Research Interests Alignment\n- Collaboration Potential\n- Symposium Participation Strategy\n- Development Roadmap\n- Active Inference Integration\n\nWould you be able to share more information about Greg Elliott's profile?",
  "metadata": {
    "participant": "Greg Elliott",
    "report_type": "profile_analysis"
  }
}