{
  "timestamp": "2025-11-11T10:56:36.744767",
  "content": "I notice that several key pieces of information about Zohreh Rahmannejad are missing from the profile provided. To create a truly personalized and effective curriculum, I'll need to understand:\n\n**Key Information Needed:**\n\n1. **Background:**\n- Academic/professional background\n- Current field of work/research\n- Mathematical/computational skill level\n- Prior exposure to related concepts (e.g., Bayesian inference, control theory)\n\n2. **Current Active Inference Application:**\n- Specific domain/problem they're working on\n- Current understanding/implementation level\n- Tools/frameworks they're using\n\n3. **Learning Needs:**\n- Specific aspects of Active Inference they want to master\n- Immediate learning priorities\n- Long-term learning goals\n\n4. **Challenges:**\n- Current obstacles in understanding/implementing Active Inference\n- Time constraints\n- Resource limitations\n\n5. **Pragmatic Value:**\n- How they plan to apply Active Inference\n- Specific problems they want to solve\n- Expected practical outcomes\n\n6. **Epistemic Value:**\n- Depth of theoretical understanding desired\n- Research interests\n- Knowledge building goals\n\nWould you be able to provide these details about Zohreh? This would allow me to create a highly tailored curriculum that:\n- Matches their current knowledge level\n- Addresses specific learning needs\n- Focuses on relevant applications\n- Provides appropriate resources\n- Sets realistic timelines\n- Offers suitable learning formats\n\nOnce these details are provided, I can design a comprehensive curriculum following the structure you've outlined.",
  "metadata": {
    "participant": "Zohreh Rahmannejad",
    "report_type": "curriculum"
  }
}